django_jazzmin_admin_rangefilter_jalali_plus-1.0.0.dist-info/licenses/LICENSE
rangefilter2/__init__.py
rangefilter2/admin.py
rangefilter2/apps.py
rangefilter2/filter.py
rangefilter2/filters.py
rangefilter2/jalali_date_range_filter.py
rangefilter2/models.py
rangefilter2/settings.py
rangefilter2/tests.py
rangefilter2/views.py
rangefilter2/locale/cs_CZ/LC_MESSAGES/django.mo
rangefilter2/locale/cs_CZ/LC_MESSAGES/django.po
rangefilter2/locale/da/LC_MESSAGES/django.mo
rangefilter2/locale/da/LC_MESSAGES/django.po
rangefilter2/locale/de/LC_MESSAGES/django.mo
rangefilter2/locale/de/LC_MESSAGES/django.po
rangefilter2/locale/el/LC_MESSAGES/django.mo
rangefilter2/locale/el/LC_MESSAGES/django.po
rangefilter2/locale/en_US/LC_MESSAGES/django.mo
rangefilter2/locale/en_US/LC_MESSAGES/django.po
rangefilter2/locale/es/LC_MESSAGES/django.mo
rangefilter2/locale/es/LC_MESSAGES/django.po
rangefilter2/locale/es_AR/LC_MESSAGES/django.mo
rangefilter2/locale/es_AR/LC_MESSAGES/django.po
rangefilter2/locale/fa/LC_MESSAGES/django.mo
rangefilter2/locale/fa/LC_MESSAGES/django.po
rangefilter2/locale/fr/LC_MESSAGES/django.mo
rangefilter2/locale/fr/LC_MESSAGES/django.po
rangefilter2/locale/it/LC_MESSAGES/django.mo
rangefilter2/locale/it/LC_MESSAGES/django.po
rangefilter2/locale/ja/LC_MESSAGES/django.mo
rangefilter2/locale/ja/LC_MESSAGES/django.po
rangefilter2/locale/pl/LC_MESSAGES/django.mo
rangefilter2/locale/pl/LC_MESSAGES/django.po
rangefilter2/locale/pt_BR/LC_MESSAGES/django.mo
rangefilter2/locale/pt_BR/LC_MESSAGES/django.po
rangefilter2/locale/pt_PT/LC_MESSAGES/django.mo
rangefilter2/locale/pt_PT/LC_MESSAGES/django.po
rangefilter2/locale/ru/LC_MESSAGES/django.mo
rangefilter2/locale/ru/LC_MESSAGES/django.po
rangefilter2/locale/uk/LC_MESSAGES/django.mo
rangefilter2/locale/uk/LC_MESSAGES/django.po
rangefilter2/locale/zh_CN/LC_MESSAGES/django.mo
rangefilter2/locale/zh_CN/LC_MESSAGES/django.po
rangefilter2/locale/zh_Hans/LC_MESSAGES/django.mo
rangefilter2/locale/zh_Hans/LC_MESSAGES/django.po
rangefilter2/migrations/__init__.py
rangefilter2/static/rangefilter2/iife.js
django_jazzmin_admin_rangefilter_jalali_plus-1.0.0.dist-info/METADATA
django_jazzmin_admin_rangefilter_jalali_plus-1.0.0.dist-info/WHEEL
django_jazzmin_admin_rangefilter_jalali_plus-1.0.0.dist-info/top_level.txt
django_jazzmin_admin_rangefilter_jalali_plus-1.0.0.dist-info/RECORD
