Metadata-Version: 2.4
Name: django-jazzmin-admin-rangefilter-jalali-plus
Version: 1.0.0
Summary: Jalali date support for Django Jazzmin admin with rangefilter
Home-page: https://github.com/sajjadmoosavi/django_jazzmin_admin_rangefilter_jalali_plus
Author: Sajjad Mousavi
Author-email: Sajjadmoosavi90@gmail.com
Classifier: Framework :: Django
Classifier: Programming Language :: Python :: 3
Classifier: Operating System :: OS Independent
License-File: LICENSE
Requires-Dist: django>=4.0
Requires-Dist: django-jalali-date>=2.0.0
Requires-Dist: django-admin-rangefilter>=0.9.0
Dynamic: author
Dynamic: author-email
Dynamic: classifier
Dynamic: description
Dynamic: description-content-type
Dynamic: home-page
Dynamic: license-file
Dynamic: requires-dist
Dynamic: summary
